{
  "id": "bachmann-bundle-block",
  "name": "Bachmann Bundle Block",
  "aliases": [
    "Bachmann's bundle block",
    "Interatrial block",
    "IAB",
    "Interatrial conduction delay",
    "Advanced interatrial block"
  ],
  "urgency": "findings",
  "category": "structural",
  "actionLabel": null,
  "identifyBy": [
    "P wave duration ≥120ms (broad, similar to P-mitrale but different mechanism)",
    "Biphasic P wave morphology in inferior leads (positive then negative) - advanced IAB (Bayes criterion)",
    "P wave changes throughout leads as interatrial conduction timing is altered",
    "First degree IAB: P wave duration ≥120ms only (similar to P-mitrale)",
    "Advanced IAB: P wave biphasic in inferior leads (positive-negative) - much higher AF risk"
  ],
  "measurements": {
    "rate": "60–90 bpm",
    "rhythm": "Regular",
    "pWaves": "Broad ≥120ms; biphasic in inferior leads (advanced IAB)",
    "prInterval": "Normal",
    "qrsDuration": "<120ms",
    "qtInterval": "Normal",
    "axis": "Normal",
    "stSegment": "Normal"
  },
  "management": [
    "Bachmann bundle block itself does not require direct treatment",
    "Advanced IAB (biphasic P in inferior leads): strong predictor of AF and cardioembolic stroke",
    "Bayes syndrome: advanced IAB + AF history = high stroke risk - cardiology referral for anticoagulation decision",
    "Screen for: LV dysfunction, LA enlargement, ischaemic heart disease (common associations)",
    "Echocardiogram: assess LA size and LV function",
    "Holter monitoring: AF detection if symptomatic (palpitations, unexplained stroke)"
  ],
  "pearls": [
    "Bachmann's bundle is the principal interatrial conduction pathway - connects right to left atrium",
    "Advanced IAB (biphasic P inferior leads) is associated with AF, stroke, and atrial cardiomyopathy",
    "Bayes syndrome = advanced IAB + history of AF → high stroke risk even if currently in sinus rhythm",
    "Distinguishing P-mitrale from Bachmann block: P-mitrale has bifid/notched P in II but positive throughout; IAB has biphasic (pos-neg) P in inferior leads",
    "P-wave duration ≥120ms is the ECG hallmark of BOTH P-mitrale and IAB - lead V1 pattern and clinical context differentiate"
  ],
  "differentials": [
    "P-mitrale (broad bifid P, positive throughout inferior leads, mitral valve disease)",
    "Biatrial enlargement (both tall and broad P)",
    "WPW with negative delta in inferior leads (short PR distinguishes)",
    "Normal P wave variant with right atrial overload in pulmonary disease"
  ],
  "relatedGuidelineIDs": [],
  "relatedCalculatorIDs": [],
  "tags": [
    "Bachmann bundle",
    "interatrial block",
    "IAB",
    "P wave",
    "AF risk",
    "Bayes syndrome",
    "ecg-v2",
    "multi-lead-authored"
  ],
  "isFreeContent": false,
  "version": 4,
  "lastUpdated": "2026-05-28T00:00:00Z",
  "waveform": {
    "engineVersion": 2,
    "rhythmFamily": "structural",
    "previewOrientation": "portrait",
    "stripSmallBoxesPortrait": 83,
    "stripSmallBoxesLandscape": 140,
    "rrPattern": "regular",
    "heartRate": 70,
    "atrialActivity": {
      "type": "discreteP",
      "pAmplitudeMm": 1.5,
      "pDurationMs": 140,
      "prMs": 160,
      "prSegmentMs": 40
    },
    "qrs": {
      "type": "narrow",
      "qAmplitudeMm": -0.35,
      "amplitudeMm": 9,
      "durationMs": 90,
      "sAmplitudeMm": -2,
      "notch": false
    },
    "st": {
      "elevationMm": 0,
      "morphology": "flat",
      "durationMs": 80
    },
    "tWave": {
      "present": true,
      "amplitudeMm": 2.5,
      "durationMs": 180,
      "shape": "normal"
    },
    "sourceUrls": [],
    "qaNotes": [
      "Structural/atrial enlargement pattern preserves P/QRS/ST-T morphology from source content."
    ],
    "qaReviewedAt": "2026-05-24T00:00:00Z",
    "qaConfidence": "pattern-reviewed",
    "mode": "multiLead",
    "multiLead": {
      "focusLead": "III",
      "leads": [
        {
          "lead": "II",
          "isDiagnosticLead": true,
          "components": {
            "pWave": {
              "durationMs": 130,
              "amplitudeMm": 1.6,
              "morphology": "biphasic"
            }
          }
        },
        {
          "lead": "III",
          "isDiagnosticLead": true,
          "components": {
            "pWave": {
              "durationMs": 140,
              "amplitudeMm": 1.8,
              "morphology": "biphasic"
            }
          }
        },
        {
          "lead": "aVF",
          "isDiagnosticLead": true,
          "components": {
            "pWave": {
              "durationMs": 140,
              "amplitudeMm": 1.8,
              "morphology": "biphasic"
            }
          }
        },
        {
          "lead": "V1",
          "isDiagnosticLead": false,
          "components": {
            "pWave": {
              "durationMs": 120,
              "amplitudeMm": 1.2,
              "morphology": "biphasic"
            }
          }
        }
      ]
    }
  }
}
